aionostr/__init__.py
aionostr/bech32.py
aionostr/benchmark.py
aionostr/cli.py
aionostr/delegation.py
aionostr/event.py
aionostr/key.py
aionostr/relay.py
aionostr/util.py
aionostr-0.20.0.dist-info/AUTHORS.rst
aionostr-0.20.0.dist-info/LICENSE
aionostr-0.20.0.dist-info/METADATA
aionostr-0.20.0.dist-info/WHEEL
aionostr-0.20.0.dist-info/entry_points.txt
aionostr-0.20.0.dist-info/top_level.txt
aionostr-0.20.0.dist-info/RECORD
